neurohive/__init__.py
neurohive/buildinfo/__init__.py
neurohive/buildinfo/info.py
neurohive/cli/__init__.py
neurohive/cli/bb_cmd.py
neurohive/cli/commands.py
neurohive/deploy/__init__.py
neurohive/deploy/compose_conv.py
neurohive/deploy/ecs.py
neurohive/deploy/kube.py
neurohive/deploy/string.py
neurohive/deploy/templates.py
neurohive/deploy/unity.py
neurohive/integration/__init__.py
neurohive/integration/appcenter.py
neurohive/integration/appstoreconnect.py
neurohive/integration/asanawrapper.py
neurohive/integration/aws.py
neurohive/integration/bitbucket.py
neurohive/integration/jirawrap.py
neurohive/integration/unitycloud.py
neurohive_devops_tools-0.0.62.dist-info/METADATA
neurohive_devops_tools-0.0.62.dist-info/WHEEL
neurohive_devops_tools-0.0.62.dist-info/entry_points.txt
neurohive_devops_tools-0.0.62.dist-info/top_level.txt
neurohive_devops_tools-0.0.62.dist-info/RECORD
